TheDigger_src/__init__.py
TheDigger_src/main.py
TheDigger_src/lib/__init__.py
TheDigger_src/lib/dns_handler.py
TheDigger_src/lib/fuzzer.py
TheDigger_src/lib/host.py
TheDigger_src/lib/owasp.py
TheDigger_src/lib/scanner.py
TheDigger_src/lib/storage_explorer.py
TheDigger_src/lib/sub_domain.py
TheDigger_src/lib/tls.py
TheDigger_src/lib/waf.py
TheDigger_src/lib/web_app.py
TheDigger_src/utils/__init__.py
TheDigger_src/utils/coloring.py
TheDigger_src/utils/exceptions.py
TheDigger_src/utils/help_utils.py
TheDigger_src/utils/logger.py
TheDigger_src/utils/request_handler.py
TheDigger_src/utils/singleton.py
TheDigger_src/utils/web_server_validator.py
TheDigger_src/wordlists/fuzzlist
TheDigger_src/wordlists/storage_sensitive
TheDigger_src/wordlists/subdomains
TheDigger-0.1.dist-info/LICENSE
TheDigger-0.1.dist-info/METADATA
TheDigger-0.1.dist-info/WHEEL
TheDigger-0.1.dist-info/entry_points.txt
TheDigger-0.1.dist-info/top_level.txt
TheDigger-0.1.dist-info/RECORD
